math_round
