Metadata-Version: 1.1
Name: math-round
Version: 0.0.3.post1
Summary: Mathematical rounding for python 3
Home-page: https://github.com/anisov/math-round
Author: Anisov Dmitriy
Author-email: dimaanisov24@gmail.com
License: MIT
Keywords: math,round,math-round
Platform: UNKNOWN
Classifier: Development Status :: 3 - Alpha
Classifier: Intended Audience :: Developers
Classifier: License :: OSI Approved :: MIT License
Classifier: Operating System :: OS Independent
Classifier: Programming Language :: Python :: 3
Classifier: Topic :: Software Development :: Libraries :: Python Modules
